telegram_bot_fast_me/__init__.py
telegram_bot_fast_me/bot.py
telegram_bot_fast_me-0.1.dist-info/LICENSE
telegram_bot_fast_me-0.1.dist-info/METADATA
telegram_bot_fast_me-0.1.dist-info/WHEEL
telegram_bot_fast_me-0.1.dist-info/top_level.txt
telegram_bot_fast_me-0.1.dist-info/RECORD
