Metadata-Version: 2.1
Name: telegram-bot-fast-me
Version: 0.1
Summary: A fast and simple library for Telegram bots
Home-page: https://github.com/yourusername/TelegramBotFastMe
Author: Your Name
Author-email: parker.trusty@echohyper.com
Classifier: Programming Language :: Python :: 3
Classifier: License :: OSI Approved :: MIT License
Classifier: Operating System :: OS Independent
License-File: LICENSE
Requires-Dist: aiohttp
